pipcreate/__init__.py
pipcreate/__main__.py
pipcreate/pipcreate.py
pipcreate-0.1.1.dist-info/DESCRIPTION.rst
pipcreate-0.1.1.dist-info/METADATA
pipcreate-0.1.1.dist-info/metadata.json
pipcreate-0.1.1.dist-info/RECORD
pipcreate-0.1.1.dist-info/top_level.txt
pipcreate-0.1.1.dist-info/WHEEL
