Metadata-Version: 2.0
Name: pipcreate
Version: 0.1.1
Summary: Automatically create a python package upload it on github, set up continuous integration so you can focus on code.
Home-page: https://github.com/Carreau/pipcreate
Author: Matthias Bussonnier
Author-email: bussonniermatthias@gmail.com
License: BSD
Keywords: pipcreate
Platform: UNKNOWN
Classifier: Development Status :: 2 - Pre-Alpha
Classifier: Intended Audience :: Developers
Classifier: License :: OSI Approved :: BSD License
Classifier: Programming Language :: Python :: 3
Classifier: Programming Language :: Python :: 3.3
Classifier: Programming Language :: Python :: 3.4
